{"node_manager_abi": [{"payable": false, "stateMutability": "nonpayable", "constant": false, "name": "withdrawFromMchains", "inputs": [], "type": "function", "outputs": []}, {"payable": false, "stateMutability": "nonpayable", "constant": false, "name": "testBytes", "inputs": [{"type": "bytes", "name": "data"}], "type": "function", "outputs": []}, {"payable": false, "stateMutability": "nonpayable", "constant": false, "name": "setNumber", "inputs": [{"type": "uint256", "name": "num"}], "type": "function", "outputs": []}, {"payable": false, "stateMutability": "view", "constant": true, "name": "getNode", "inputs": [{"type": "uint256", "name": "index"}], "type": "function", "outputs": [{"type": "bytes15", "name": ""}, {"type": "uint16", "name": ""}, {"type": "uint8", "name": ""}, {"type": "bytes", "name": ""}, {"type": "uint256", "name": ""}, {"type": "uint256", "name": ""}]}, {"payable": false, "stateMutability": "view", "constant": true, "name": "getActiveNodeIPs", "inputs": [{"type": "uint256[]", "name": "id"}], "type": "function", "outputs": [{"type": "bytes15[]", "name": "arr"}]}, {"payable": false, "stateMutability": "view", "constant": true, "name": "getActiveNodeIDs", "inputs": [], "type": "function", "outputs": [{"type": "uint256[]", "name": "arr"}]}, {"payable": false, "stateMutability": "view", "constant": true, "name": "DEPOSIT_VALUE", "inputs": [], "type": "function", "outputs": [{"type": "uint256", "name": ""}]}, {"payable": false, "stateMutability": "view", "constant": true, "name": "getAggregationMchain", "inputs": [{"type": "uint256", "name": "index"}], "type": "function", "outputs": [{"type": "address", "name": ""}, {"type": "uint256", "name": ""}, {"type": "uint256", "name": ""}, {"type": "uint256", "name": ""}, {"type": "uint256", "name": ""}, {"type": "uint256", "name": ""}]}, {"payable": false, "stateMutability": "pure", "constant": true, "name": "fallbackOperationTypeConvert", "inputs": [{"type": "bytes", "name": "data"}], "type": "function", "outputs": [{"type": "uint8", "name": ""}]}, {"payable": false, "stateMutability": "view", "constant": true, "name": "getMchainListFromAggregationMchain", "inputs": [{"type": "uint256", "name": "index"}], "type": "function", "outputs": [{"type": "uint256[]", "name": ""}]}, {"payable": false, "stateMutability": "nonpayable", "constant": false, "name": "initWithdrawDeposit", "inputs": [{"type": "uint256", "name": "nodeNumber"}], "type": "function", "outputs": []}, {"payable": false, "stateMutability": "nonpayable", "constant": false, "name": "withdrawFromMchain", "inputs": [{"type": "uint256", "name": "index"}], "type": "function", "outputs": []}, {"payable": false, "stateMutability": "nonpayable", "constant": false, "name": "completeWithdrawDeposit", "inputs": [{"type": "uint256", "name": "nodeNumber"}], "type": "function", "outputs": []}, {"payable": false, "stateMutability": "nonpayable", "constant": false, "name": "tokenFallback", "inputs": [{"type": "address", "name": "_from"}, {"type": "uint256", "name": "_value"}, {"type": "bytes", "name": "_data"}], "type": "function", "outputs": []}, {"payable": false, "stateMutability": "view", "constant": true, "name": "getMchain", "inputs": [{"type": "uint256", "name": "index"}], "type": "function", "outputs": [{"type": "address", "name": ""}, {"type": "uint256", "name": ""}, {"type": "uint256", "name": ""}, {"type": "uint256", "name": ""}, {"type": "uint256", "name": ""}, {"type": "uint256", "name": ""}]}, {"payable": false, "stateMutability": "nonpayable", "constant": false, "name": "heartbit", "inputs": [{"type": "uint256", "name": "nodeNumber"}], "type": "function", "outputs": []}, {"payable": false, "stateMutability": "nonpayable", "constant": false, "name": "addToAggregationMchain", "inputs": [{"type": "uint256", "name": "aggregationMchainID"}, {"type": "uint256", "name": "mchainID"}, {"type": "uint16", "name": "nonce"}], "type": "function", "outputs": []}, {"payable": false, "stateMutability": "view", "constant": true, "name": "getAggregationMchainList", "inputs": [], "type": "function", "outputs": [{"type": "uint256[]", "name": ""}]}, {"payable": false, "stateMutability": "view", "constant": true, "name": "getActiveNodeIPs", "inputs": [], "type": "function", "outputs": [{"type": "bytes15[]", "name": "arr"}]}, {"payable": false, "stateMutability": "nonpayable", "constant": false, "name": "withdrawFromAggregationMchain", "inputs": [{"type": "uint256", "name": "index"}], "type": "function", "outputs": []}, {"payable": false, "stateMutability": "pure", "constant": true, "name": "fallbackCreateNodeDataConvert", "inputs": [{"type": "bytes", "name": "data"}], "type": "function", "outputs": [{"type": "uint16", "name": ""}, {"type": "uint16", "name": ""}, {"type": "bytes15", "name": ""}]}, {"payable": false, "stateMutability": "view", "constant": true, "name": "getMchainList", "inputs": [], "type": "function", "outputs": [{"type": "uint256[]", "name": ""}]}, {"payable": false, "stateMutability": "nonpayable", "constant": false, "name": "getNumber", "inputs": [], "type": "function", "outputs": [{"type": "uint256", "name": ""}]}, {"payable": false, "stateMutability": "nonpayable", "constant": false, "name": "createNode", "inputs": [{"type": "address", "name": "_from"}, {"type": "uint256", "name": "_value"}, {"type": "bytes", "name": "_data"}], "type": "function", "outputs": []}, {"payable": false, "stateMutability": "nonpayable", "inputs": [{"type": "address", "name": "_token"}, {"type": "uint256", "name": "_annualMint"}], "type": "constructor"}, {"type": "event", "name": "Test1", "inputs": [], "anonymous": false}, {"type": "event", "name": "Test2", "inputs": [], "anonymous": false}, {"type": "event", "name": "NodeCreated", "inputs": [{"type": "uint256", "name": "nodeID", "indexed": false}, {"type": "address", "name": "owner", "indexed": false}, {"type": "bytes15", "name": "ip", "indexed": false}, {"type": "uint16", "name": "port", "indexed": false}, {"type": "uint16", "name": "nonce", "indexed": false}], "anonymous": false}, {"type": "event", "name": "MchainCreated", "inputs": [{"type": "uint256", "name": "mchainID", "indexed": false}, {"type": "address", "name": "owner", "indexed": false}, {"type": "uint256", "name": "storageBytes", "indexed": false}, {"type": "uint256", "name": "lifetime", "indexed": false}, {"type": "uint256", "name": "maxNodes", "indexed": false}, {"type": "uint256", "name": "deposit", "indexed": false}, {"type": "uint16", "name": "nonce", "indexed": false}, {"type": "bytes32", "name": "name", "indexed": false}], "anonymous": false}, {"type": "event", "name": "AggregationMchainCreated", "inputs": [{"type": "uint256", "name": "mchainID", "indexed": false}, {"type": "address", "name": "owner", "indexed": false}, {"type": "uint256", "name": "storageBytes", "indexed": false}, {"type": "uint256", "name": "lifetime", "indexed": false}, {"type": "uint256", "name": "maxNodes", "indexed": false}, {"type": "uint256", "name": "deposit", "indexed": false}, {"type": "uint16", "name": "nonce", "indexed": false}, {"type": "bytes32", "name": "name", "indexed": false}], "anonymous": false}, {"type": "event", "name": "MchainAdded", "inputs": [{"type": "uint256", "name": "aggregationMchainID", "indexed": false}, {"type": "uint256", "name": "mchainID", "indexed": false}, {"type": "uint16", "name": "nonce", "indexed": false}], "anonymous": false}, {"type": "event", "name": "NumberEvent", "inputs": [{"type": "uint256", "name": "num", "indexed": false}], "anonymous": false}, {"type": "event", "name": "BytesEvent", "inputs": [{"type": "bytes", "name": "data", "indexed": false}], "anonymous": false}], "token_abi": [{"payable": false, "stateMutability": "view", "constant": true, "name": "name", "inputs": [], "type": "function", "outputs": [{"type": "string", "name": ""}]}, {"payable": false, "stateMutability": "nonpayable", "constant": false, "name": "approve", "inputs": [{"type": "address", "name": "_spender"}, {"type": "uint256", "name": "_value"}], "type": "function", "outputs": [{"type": "bool", "name": ""}]}, {"payable": false, "stateMutability": "view", "constant": true, "name": "totalSupply", "inputs": [], "type": "function", "outputs": [{"type": "uint256", "name": ""}]}, {"payable": false, "stateMutability": "nonpayable", "constant": false, "name": "transferFrom", "inputs": [{"type": "address", "name": "_from"}, {"type": "address", "name": "_to"}, {"type": "uint256", "name": "_value"}], "type": "function", "outputs": [{"type": "bool", "name": ""}]}, {"payable": false, "stateMutability": "view", "constant": true, "name": "decimals", "inputs": [], "type": "function", "outputs": [{"type": "uint256", "name": ""}]}, {"payable": false, "stateMutability": "view", "constant": true, "name": "cap", "inputs": [], "type": "function", "outputs": [{"type": "uint256", "name": ""}]}, {"payable": false, "stateMutability": "nonpayable", "constant": false, "name": "mint", "inputs": [{"type": "address", "name": "_to"}, {"type": "uint256", "name": "_amount"}], "type": "function", "outputs": [{"type": "bool", "name": ""}]}, {"payable": false, "stateMutability": "view", "constant": true, "name": "balanceOf", "inputs": [{"type": "address", "name": "_owner"}], "type": "function", "outputs": [{"type": "uint256", "name": ""}]}, {"payable": false, "stateMutability": "view", "constant": true, "name": "owner", "inputs": [], "type": "function", "outputs": [{"type": "address", "name": ""}]}, {"payable": false, "stateMutability": "view", "constant": true, "name": "symbol", "inputs": [], "type": "function", "outputs": [{"type": "string", "name": ""}]}, {"payable": false, "stateMutability": "nonpayable", "constant": false, "name": "burn", "inputs": [{"type": "address", "name": "_from"}, {"type": "uint256", "name": "_amount"}], "type": "function", "outputs": [{"type": "bool", "name": ""}]}, {"payable": false, "stateMutability": "nonpayable", "constant": false, "name": "transfer", "inputs": [{"type": "address", "name": "_to"}, {"type": "uint256", "name": "_value"}], "type": "function", "outputs": [{"type": "bool", "name": ""}]}, {"payable": false, "stateMutability": "nonpayable", "constant": false, "name": "transfer", "inputs": [{"type": "address", "name": "_to"}, {"type": "uint256", "name": "_value"}, {"type": "bytes", "name": "_data"}], "type": "function", "outputs": [{"type": "bool", "name": ""}]}, {"payable": false, "stateMutability": "view", "constant": true, "name": "allowance", "inputs": [{"type": "address", "name": "_owner"}, {"type": "address", "name": "_spender"}], "type": "function", "outputs": [{"type": "uint256", "name": ""}]}, {"payable": false, "stateMutability": "nonpayable", "constant": false, "name": "transferOwnership", "inputs": [{"type": "address", "name": "newOwner"}], "type": "function", "outputs": []}, {"payable": false, "stateMutability": "nonpayable", "inputs": [], "type": "constructor"}, {"type": "event", "name": "Mint", "inputs": [{"type": "address", "name": "to", "indexed": true}, {"type": "uint256", "name": "amount", "indexed": false}], "anonymous": false}, {"type": "event", "name": "Burn", "inputs": [{"type": "address", "name": "from", "indexed": true}, {"type": "uint256", "name": "amount", "indexed": false}], "anonymous": false}, {"type": "event", "name": "Transfer", "inputs": [{"type": "address", "name": "_from", "indexed": true}, {"type": "address", "name": "_to", "indexed": true}, {"type": "uint256", "name": "_value", "indexed": false}, {"type": "bytes", "name": "_data", "indexed": false}], "anonymous": false}, {"type": "event", "name": "Approval", "inputs": [{"type": "address", "name": "_owner", "indexed": true}, {"type": "address", "name": "_spender", "indexed": true}, {"type": "uint256", "name": "_value", "indexed": false}], "anonymous": false}], "token_address": "0x6f11DD715845299212817c5694547009db8125dA", "node_manager_address": "0xdfeeDec2ef56De791345AB0CeC184a1D863Af7cf"}