{"node_manager_abi": [{"inputs": [{"name": "aggregationChannelID", "type": "uint256"}, {"name": "basicChannelID", "type": "uint256"}, {"name": "nonce", "type": "uint16"}], "stateMutability": "nonpayable", "name": "addToAggregationChannel", "outputs": [], "constant": false, "type": "function", "payable": false}, {"inputs": [], "stateMutability": "view", "name": "getNodeIPs", "outputs": [{"name": "", "type": "bytes16[]"}], "constant": true, "type": "function", "payable": false}, {"inputs": [], "stateMutability": "nonpayable", "name": "withdrawFromChannels", "outputs": [], "constant": false, "type": "function", "payable": false}, {"inputs": [{"name": "nodeNumber", "type": "uint256"}], "stateMutability": "nonpayable", "name": "initWithdrawDeposit", "outputs": [], "constant": false, "type": "function", "payable": false}, {"inputs": [{"name": "nodeNumber", "type": "uint256"}], "stateMutability": "nonpayable", "name": "completeWithdrawDeposit", "outputs": [], "constant": false, "type": "function", "payable": false}, {"inputs": [{"name": "_from", "type": "address"}, {"name": "_value", "type": "uint256"}, {"name": "_data", "type": "bytes"}], "stateMutability": "nonpayable", "name": "tokenFallback", "outputs": [], "constant": false, "type": "function", "payable": false}, {"inputs": [{"name": "nodeNumber", "type": "uint256"}], "stateMutability": "nonpayable", "name": "heartbit", "outputs": [], "constant": false, "type": "function", "payable": false}, {"inputs": [{"name": "_token", "type": "address"}, {"name": "_annualMint", "type": "uint256"}], "stateMutability": "nonpayable", "payable": false, "type": "constructor"}, {"inputs": [{"name": "nodeID", "type": "uint256", "indexed": false}, {"name": "owner", "type": "address", "indexed": false}, {"name": "ip", "type": "bytes15", "indexed": false}, {"name": "port", "type": "uint16", "indexed": false}, {"name": "nonce", "type": "uint16", "indexed": false}], "name": "NodeCreated", "anonymous": false, "type": "event"}, {"inputs": [{"name": "channelID", "type": "uint256", "indexed": false}, {"name": "owner", "type": "address", "indexed": false}, {"name": "storageBytes", "type": "uint256", "indexed": false}, {"name": "lifetime", "type": "uint256", "indexed": false}, {"name": "maxNodes", "type": "uint256", "indexed": false}, {"name": "deposit", "type": "uint256", "indexed": false}, {"name": "nonce", "type": "uint16", "indexed": false}], "name": "BasicChannelCreated", "anonymous": false, "type": "event"}, {"inputs": [{"name": "channelID", "type": "uint256", "indexed": false}, {"name": "owner", "type": "address", "indexed": false}, {"name": "storageBytes", "type": "uint256", "indexed": false}, {"name": "lifetime", "type": "uint256", "indexed": false}, {"name": "maxNodes", "type": "uint256", "indexed": false}, {"name": "deposit", "type": "uint256", "indexed": false}, {"name": "nonce", "type": "uint16", "indexed": false}], "name": "AggregationChannelCreated", "anonymous": false, "type": "event"}, {"inputs": [{"name": "aggregationChannelID", "type": "uint256", "indexed": false}, {"name": "basicChannelID", "type": "uint256", "indexed": false}, {"name": "nonce", "type": "uint16", "indexed": false}], "name": "BasicChannelAdded", "anonymous": false, "type": "event"}], "node_manager_address": "0x6f685ed6d4b357794cd005963f13d781b5a80efd", "token_address": "0x0c1431c5cbdc75067595af8301b299bf9fb6c10d", "token_abi": [{"inputs": [], "stateMutability": "view", "name": "name", "outputs": [{"name": "", "type": "string"}], "constant": true, "type": "function", "payable": false}, {"inputs": [{"name": "_spender", "type": "address"}, {"name": "_value", "type": "uint256"}], "stateMutability": "nonpayable", "name": "approve", "outputs": [{"name": "", "type": "bool"}], "constant": false, "type": "function", "payable": false}, {"inputs": [], "stateMutability": "view", "name": "totalSupply", "outputs": [{"name": "", "type": "uint256"}], "constant": true, "type": "function", "payable": false}, {"inputs": [{"name": "_from", "type": "address"}, {"name": "_to", "type": "address"}, {"name": "_value", "type": "uint256"}], "stateMutability": "nonpayable", "name": "transferFrom", "outputs": [{"name": "", "type": "bool"}], "constant": false, "type": "function", "payable": false}, {"inputs": [], "stateMutability": "view", "name": "decimals", "outputs": [{"name": "", "type": "uint256"}], "constant": true, "type": "function", "payable": false}, {"inputs": [], "stateMutability": "view", "name": "cap", "outputs": [{"name": "", "type": "uint256"}], "constant": true, "type": "function", "payable": false}, {"inputs": [{"name": "_to", "type": "address"}, {"name": "_amount", "type": "uint256"}], "stateMutability": "nonpayable", "name": "mint", "outputs": [{"name": "", "type": "bool"}], "constant": false, "type": "function", "payable": false}, {"inputs": [{"name": "_owner", "type": "address"}], "stateMutability": "view", "name": "balanceOf", "outputs": [{"name": "", "type": "uint256"}], "constant": true, "type": "function", "payable": false}, {"inputs": [], "stateMutability": "view", "name": "owner", "outputs": [{"name": "", "type": "address"}], "constant": true, "type": "function", "payable": false}, {"inputs": [], "stateMutability": "view", "name": "symbol", "outputs": [{"name": "", "type": "string"}], "constant": true, "type": "function", "payable": false}, {"inputs": [{"name": "_from", "type": "address"}, {"name": "_amount", "type": "uint256"}], "stateMutability": "nonpayable", "name": "burn", "outputs": [{"name": "", "type": "bool"}], "constant": false, "type": "function", "payable": false}, {"inputs": [{"name": "_to", "type": "address"}, {"name": "_value", "type": "uint256"}], "stateMutability": "nonpayable", "name": "transfer", "outputs": [{"name": "", "type": "bool"}], "constant": false, "type": "function", "payable": false}, {"inputs": [{"name": "_to", "type": "address"}, {"name": "_value", "type": "uint256"}, {"name": "_data", "type": "bytes"}], "stateMutability": "nonpayable", "name": "transfer", "outputs": [{"name": "", "type": "bool"}], "constant": false, "type": "function", "payable": false}, {"inputs": [{"name": "_owner", "type": "address"}, {"name": "_spender", "type": "address"}], "stateMutability": "view", "name": "allowance", "outputs": [{"name": "", "type": "uint256"}], "constant": true, "type": "function", "payable": false}, {"inputs": [{"name": "newOwner", "type": "address"}], "stateMutability": "nonpayable", "name": "transferOwnership", "outputs": [], "constant": false, "type": "function", "payable": false}, {"inputs": [], "stateMutability": "nonpayable", "payable": false, "type": "constructor"}, {"inputs": [{"name": "to", "type": "address", "indexed": true}, {"name": "amount", "type": "uint256", "indexed": false}], "name": "Mint", "anonymous": false, "type": "event"}, {"inputs": [{"name": "from", "type": "address", "indexed": true}, {"name": "amount", "type": "uint256", "indexed": false}], "name": "Burn", "anonymous": false, "type": "event"}, {"inputs": [{"name": "_from", "type": "address", "indexed": true}, {"name": "_to", "type": "address", "indexed": true}, {"name": "_value", "type": "uint256", "indexed": false}, {"name": "_data", "type": "bytes", "indexed": false}], "name": "Transfer", "anonymous": false, "type": "event"}, {"inputs": [{"name": "_owner", "type": "address", "indexed": true}, {"name": "_spender", "type": "address", "indexed": true}, {"name": "_value", "type": "uint256", "indexed": false}], "name": "Approval", "anonymous": false, "type": "event"}]}